lite_fastapi_local/QR_CHK_dep.py
lite_fastapi_local/QR_END_dep.py
lite_fastapi_local/QR_READ_dep.py
lite_fastapi_local/__init__.py
lite_fastapi_local/main.py
lite_fastapi_local/requirements.txt
lite_fastapi_local/settings.py
lite_fastapi_local/common/__init__.py
lite_fastapi_local/common/function.py
lite_fastapi_local/common/variable.py
lite_fastapi_local/model/__init__.py
lite_fastapi_local/model/boxDoorModel.py
lite_fastapi_local/model/drimmLedModel.py
lite_fastapi_local/model/innerLedModel.py
lite_fastapi_local/model/motorModel.py
lite_fastapi_local/model/registrationModel.py
lite_fastapi_local/model/setupModel.py
lite_fastapi_local/model/solModel.py
lite_fastapi_local/model/sprayModel.py
lite_fastapi_local/router/__init__.py
lite_fastapi_local/router/motorRouter.py
lite_fastapi_local/router/sensorRouter.py
lite_fastapi_local/router/setupRouter.py
lite_fastapi_local/schema/qrSchema.py
lite_fastapi_local/schema/setupSchema.py
lite_fastapi_local-0.0.50.dist-info/METADATA
lite_fastapi_local-0.0.50.dist-info/WHEEL
lite_fastapi_local-0.0.50.dist-info/licenses/LICENSE
lite_fastapi_local-0.0.50.dist-info/RECORD
