Metadata-Version: 2.1
Name: lite_fastapi_local
Version: 0.0.50
Summary: A small example package
Author-email: dohyung102 <dohyung102@thegreet.co.kr>
License-File: LICENSE
Classifier: License :: OSI Approved :: MIT License
Classifier: Operating System :: OS Independent
Classifier: Programming Language :: Python :: 3
Requires-Python: >=3.7
Requires-Dist: anyio>=3.6.2
Requires-Dist: boto3>=1.26.90
Requires-Dist: botocore>=1.29.90
Requires-Dist: certifi>=2022.12.7
Requires-Dist: charset-normalizer>=3.0.1
Requires-Dist: click>=8.1.3
Requires-Dist: colorama>=0.4.6
Requires-Dist: comtypes>=1.1.14
Requires-Dist: fastapi-mqtt>=1.0.7
Requires-Dist: fastapi-utils>=0.2.1
Requires-Dist: fastapi>=0.89.1
Requires-Dist: gmqtt>=0.6.11
Requires-Dist: greenlet>=2.0.2
Requires-Dist: h11>=0.14.0
Requires-Dist: idna>=3.4
Requires-Dist: imageio>=2.25.1
Requires-Dist: jmespath>=1.0.1
Requires-Dist: lazy-loader>=0.1
Requires-Dist: networkx>=3.0
Requires-Dist: numpy>=1.24.2
Requires-Dist: opencv-python>=4.7.0.68
Requires-Dist: packaging>=23.0
Requires-Dist: pillow>=9.4.0
Requires-Dist: pydantic>=1.10.5
Requires-Dist: pygrabber>=0.1
Requires-Dist: pynput>=1.7.6
Requires-Dist: pyserial>=3.5
Requires-Dist: python-dateutil>=2.8.2
Requires-Dist: pywavelets>=1.4.1
Requires-Dist: requests>=2.28.2
Requires-Dist: s3transfer>=0.6.0
Requires-Dist: scikit-image>=0.20.0
Requires-Dist: scipy>=1.10.1
Requires-Dist: six>=1.16.0
Requires-Dist: sniffio>=1.3.0
Requires-Dist: sqlalchemy>=1.4.46
Requires-Dist: starlette>=0.22.0
Requires-Dist: tifffile>=2023.2.3
Requires-Dist: typing-extensions>=4.5.0
Requires-Dist: urllib3>=1.26.14
Requires-Dist: uvicorn>=0.20.0
